{
	"textures": {
		"3": "animated_java:blueprint/fine_print/fine_print",
		"particle": "minecraft:item/pufferfish"
	},
	"display": {
		"head": {
			"rotation": [0, 180, 0]
		}
	},
	"elements": [
		{
			"from": [3, 5, 5],
			"to": [8, 10, 11],
			"rotation": {
				"angle": 0,
				"axis": "y",
				"origin": [7, 5, 6]
			},
			"faces": {
				"north": {
					"uv": [10.5, 7.5, 11.75, 8.75],
					"texture": "#3"
				},
				"east": {
					"uv": [0, 9, 1.5, 10.25],
					"texture": "#3"
				},
				"south": {
					"uv": [8.75, 10.5, 10, 11.75],
					"texture": "#3"
				},
				"west": {
					"uv": [9, 5.25, 10.5, 6.5],
					"texture": "#3"
				},
				"up": {
					"uv": [10.5, 8, 9.25, 6.5],
					"texture": "#3"
				},
				"down": {
					"uv": [10.5, 8, 9.25, 9.5],
					"texture": "#3"
				}
			}
		},
		{
			"from": [4, -3, 6],
			"to": [7, 5, 10],
			"rotation": {
				"angle": 0,
				"axis": "y",
				"origin": [7, 0, 6]
			},
			"faces": {
				"north": {
					"uv": [11.25, 1, 12, 3],
					"texture": "#3"
				},
				"east": {
					"uv": [3.25, 8.5, 4.25, 10.5],
					"texture": "#3"
				},
				"south": {
					"uv": [5.25, 11.25, 6, 13.25],
					"texture": "#3"
				},
				"west": {
					"uv": [4.25, 8.5, 5.25, 10.5],
					"texture": "#3"
				},
				"up": {
					"uv": [13, 13.25, 12.25, 12.25],
					"texture": "#3"
				},
				"down": {
					"uv": [5, 12.5, 4.25, 13.5],
					"texture": "#3"
				}
			}
		},
		{
			"from": [3.7, -8, 5.5],
			"to": [7.7, -3, 10.5],
			"rotation": {
				"angle": 0,
				"axis": "y",
				"origin": [7.2, -8, 6]
			},
			"faces": {
				"north": {
					"uv": [11.75, 3, 12.75, 4.25],
					"texture": "#3"
				},
				"east": {
					"uv": [10, 10.5, 11.25, 11.75],
					"texture": "#3"
				},
				"south": {
					"uv": [3.25, 11.75, 4.25, 13],
					"texture": "#3"
				},
				"west": {
					"uv": [1.25, 11, 2.5, 12.25],
					"texture": "#3"
				},
				"up": {
					"uv": [12.75, 5.5, 11.75, 4.25],
					"texture": "#3"
				},
				"down": {
					"uv": [12.75, 5.5, 11.75, 6.75],
					"texture": "#3"
				}
			}
		}
	]
}