{
	"textures": {
		"0": "animated_java:item/wander/wandering_murderer"
	},
	"display": {
		"head": {
			"rotation": [0, 180, 0]
		}
	},
	"elements": [
		{
			"from": [5, -9.5, 4.58333],
			"to": [11, 8.5, 11.58333],
			"rotation": {
				"angle": 0,
				"axis": "y",
				"origin": [12, 5.5, 6.83333]
			},
			"faces": {
				"north": {
					"uv": [2.125, 7.5625, 2.5, 8.6875],
					"texture": "#0"
				},
				"east": {
					"uv": [0.5, 7.75, 0.9375, 8.875],
					"texture": "#0"
				},
				"south": {
					"uv": [8.125, 2.4375, 8.5, 3.5625],
					"texture": "#0"
				},
				"west": {
					"uv": [3.5, 7.75, 3.9375, 8.875],
					"texture": "#0"
				},
				"up": {
					"uv": [10.5, 7.5, 10.125, 7.0625],
					"texture": "#0"
				},
				"down": {
					"uv": [10.5, 7.5, 10.125, 7.9375],
					"texture": "#0"
				}
			}
		},
		{
			"from": [6, 6.5, 3.08333],
			"to": [10, 11.5, 10.33333],
			"rotation": {
				"angle": 0,
				"axis": "y",
				"origin": [11, 24.5, 6.58333]
			},
			"faces": {
				"north": {
					"uv": [11.0625, 5.375, 11.3125, 5.6875],
					"texture": "#0"
				},
				"east": {
					"uv": [10.5, 6.125, 10.9375, 6.4375],
					"texture": "#0"
				},
				"south": {
					"uv": [11.0625, 5.6875, 11.3125, 6],
					"texture": "#0"
				},
				"west": {
					"uv": [10.5, 7.0625, 10.9375, 7.375],
					"texture": "#0"
				},
				"up": {
					"uv": [9.3125, 3.625, 9.0625, 3.1875],
					"texture": "#0"
				},
				"down": {
					"uv": [4.5, 10.8125, 4.25, 11.25],
					"texture": "#0"
				}
			}
		},
		{
			"from": [3.99, -4.51, 7.32333],
			"to": [12.01, 5.01, 12.34333],
			"rotation": {
				"angle": 0,
				"axis": "y",
				"origin": [13, 5.5, 7.58333]
			},
			"faces": {
				"north": {
					"uv": [2, 8.6875, 2.5, 9.3125],
					"texture": "#0"
				},
				"east": {
					"uv": [7.625, 9.75, 7.9375, 10.375],
					"texture": "#0"
				},
				"south": {
					"uv": [4.6875, 8.6875, 5.1875, 9.3125],
					"texture": "#0"
				},
				"west": {
					"uv": [7.9375, 9.75, 8.25, 10.375],
					"texture": "#0"
				},
				"up": {
					"uv": [10.875, 2.9375, 10.375, 2.625],
					"texture": "#0"
				},
				"down": {
					"uv": [10.875, 2.9375, 10.375, 3.25],
					"texture": "#0"
				}
			}
		},
		{
			"from": [4.5, -7.5, 4.08333],
			"to": [11.5, -5.5, 12.08333],
			"rotation": {
				"angle": 0,
				"axis": "y",
				"origin": [11.5, -1.5, 4.08333]
			},
			"faces": {
				"north": {
					"uv": [11.375, 6.125, 11.8125, 6.25],
					"texture": "#0"
				},
				"east": {
					"uv": [11.25, 11.1875, 11.75, 11.3125],
					"texture": "#0"
				},
				"south": {
					"uv": [11.375, 7.5, 11.8125, 7.625],
					"texture": "#0"
				},
				"west": {
					"uv": [11.3125, 3.625, 11.8125, 3.75],
					"texture": "#0"
				},
				"up": {
					"uv": [10.125, 4.8125, 9.6875, 4.3125],
					"texture": "#0"
				},
				"down": {
					"uv": [10.125, 4.8125, 9.6875, 5.3125],
					"texture": "#0"
				}
			}
		}
	]
}