{
	"model": {
		"type": "minecraft:select",
		"property": "minecraft:custom_model_data",
		"cases": [
			{
				"when": "AJ_INTERNAL_EMPTY",
				"model": {
					"type": "minecraft:model",
					"model": "animated_java:empty"
				}
			},
			{
				"when": "2_1",
				"model": {
					"type": "minecraft:model",
					"model": "animated_java:blueprint/phil_machine/2_1/num2",
					"tints": [
						{"type": "minecraft:dye", "default": [1, 1, 1]}
					]
				}
			},
			{
				"when": "2_2",
				"model": {
					"type": "minecraft:model",
					"model": "animated_java:blueprint/phil_machine/2_2/num2",
					"tints": [
						{"type": "minecraft:dye", "default": [1, 1, 1]}
					]
				}
			},
			{
				"when": "2_3",
				"model": {
					"type": "minecraft:model",
					"model": "animated_java:blueprint/phil_machine/2_3/num2",
					"tints": [
						{"type": "minecraft:dye", "default": [1, 1, 1]}
					]
				}
			},
			{
				"when": "2_4",
				"model": {
					"type": "minecraft:model",
					"model": "animated_java:blueprint/phil_machine/2_4/num2",
					"tints": [
						{"type": "minecraft:dye", "default": [1, 1, 1]}
					]
				}
			},
			{
				"when": "2_5",
				"model": {
					"type": "minecraft:model",
					"model": "animated_java:blueprint/phil_machine/2_5/num2",
					"tints": [
						{"type": "minecraft:dye", "default": [1, 1, 1]}
					]
				}
			},
			{
				"when": "blank",
				"model": {
					"type": "minecraft:model",
					"model": "animated_java:blueprint/phil_machine/blank/num2",
					"tints": [
						{"type": "minecraft:dye", "default": [1, 1, 1]}
					]
				}
			}
		],
		"fallback": {
			"type": "minecraft:model",
			"model": "animated_java:blueprint/phil_machine/num2",
			"tints": [
				{"type": "minecraft:dye", "default": [1, 1, 1]}
			]
		}
	}
}